Metadata-Version: 1.1
Name: alogs
Version: 3.3
Summary: Custom Logging Module
Home-page: https://bitbucket.org/alana-ai/alogs
Author: Marcellus Amadeus
Author-email: marcellus@alana.ai
License: UNKNOWN
Download-URL: https://bitbucket.org/alana-ai/alogs/archive/v3.3.tar.gz
Keywords: logging
Platform: os x
Platform: linux
Platform: windows
Classifier: Environment :: Console
Classifier: Development Status :: 5 - Production/Stable
Classifier: Topic :: Utilities
Classifier: Operating System :: Unix
Classifier: Programming Language :: Python :: 3.5
Classifier: License :: OSI Approved :: MIT License
